odd_ge_adapter/__init__.py
odd_ge_adapter/__main__.py
odd_ge_adapter/adapters/__init__.py
odd_ge_adapter/adapters/s3/__init__.py
odd_ge_adapter/adapters/s3/adapter.py
odd_ge_adapter/domain/__init__.py
odd_ge_adapter/domain/expectation.py
odd_ge_adapter/domain/odd_metadata.py
odd_ge_adapter/domain/plugin.py
odd_ge_adapter/domain/run_result.py
odd_ge_adapter/domain/s3_uri.py
odd_ge_adapter/domain/suite.py
odd_ge_adapter/error.py
odd_ge_adapter/mappers/__init__.py
odd_ge_adapter/mappers/map_result.py
odd_ge_adapter/mappers/map_suite.py
odd_ge_adapter/mappers/s3_uri_to_oddrn.py
odd_ge_adapter/oddrn.py
odd_ge_adapter/storage/__init__.py
odd_ge_adapter/storage/local_storage.py
odd_ge_adapter/utils/__init__.py
odd_ge_adapter/utils/secret.py
odd_ge_adapter-0.2.13.dist-info/LICENSE
odd_ge_adapter-0.2.13.dist-info/WHEEL
odd_ge_adapter-0.2.13.dist-info/METADATA
odd_ge_adapter-0.2.13.dist-info/RECORD
