Metadata-Version: 2.1
Name: odd-ge-adapter
Version: 0.2.13
Summary: ODD adapter to Great Expectations
Home-page: https://github.com/opendatadiscovery/odd-ge-adapter
License: Apache-2.0
Keywords: great expectations,metadata,odd,open data discovery
Author: Open Data Discovery
Author-email: pypi@opendatadiscovery.org
Requires-Python: >=3.7,<4.0
Classifier: License :: OSI Approved :: Apache Software License
Classifier: Programming Language :: Python :: 3
Classifier: Programming Language :: Python :: 3.10
Classifier: Programming Language :: Python :: 3.7
Classifier: Programming Language :: Python :: 3.8
Classifier: Programming Language :: Python :: 3.9
Requires-Dist: black (>=22.3.0,<23.0.0)
Requires-Dist: boto3 (==1.21.21)
Requires-Dist: odd-collector-sdk (==0.2.6)
Requires-Dist: oddrn-generator (>=0.1.37,<0.2.0)
Requires-Dist: pytest (>=7.1.2,<8.0.0)
Requires-Dist: s3 (>=3.0.0,<4.0.0)
Project-URL: Repository, https://github.com/opendatadiscovery/odd-ge-adapter
